[
  {
    "id": "netanya_pub_1",
    "lat": 32.3523774,
    "lon": 34.865835,
    "name": "מקלט 1 - הרימון 20",
    "address": "הרימון 20",
    "city": "נתניה",
    "neighborhood": "",
    "capacity": "",
    "type": "מקלט ציבורי",
    "source": "gov",
    "category": "public"
  },
  {
    "id": "netanya_pub_3",
    "lat": 32.3506921,
    "lon": 34.8590696,
    "name": "מקלט 3 - הנרקיס 3",
    "address": "הנרקיס 3",
    "city": "נתניה",
    "neighborhood": "עין התכלת",
    "capacity": "",
    "type": "מקלט ציבורי",
    "source": "gov",
    "category": "public"
  },
  {
    "id": "netanya_pub_4",
    "lat": 32.3506921,
    "lon": 34.8590696,
    "name": "מקלט 4 - הנרקיס 9",
    "address": "הנרקיס 9",
    "city": "נתניה",
    "neighborhood": "עין התכלת",
    "capacity": "",
    "type": "מקלט ציבורי",
    "source": "gov",
    "category": "public"
  },
  {
    "id": "netanya_pub_6",
    "lat": 32.3503562,
    "lon": 34.8628662,
    "name": "מקלט 6 - הזית 1",
    "address": "הזית 1",
    "city": "נתניה",
    "neighborhood": "עין התכלת",
    "capacity": "",
    "type": "מקלט ציבורי",
    "source": "gov",
    "category": "public"
  },
  {
    "id": "netanya_pub_7",
    "lat": 32.3496494,
    "lon": 34.8602368,
    "name": "מקלט 7 - הרקפת 2",
    "address": "הרקפת 2",
    "city": "נתניה",
    "neighborhood": "עין התכלת",
    "capacity": "",
    "type": "מקלט ציבורי",
    "source": "gov",
    "category": "public"
  },
  {
    "id": "netanya_pub_8",
    "lat": 32.3330042,
    "lon": 34.8624106,
    "name": "מקלט 8 - החשמונאים",
    "address": "החשמונאים",
    "city": "נתניה",
    "neighborhood": "",
    "capacity": "",
    "type": "מקלט ציבורי",
    "source": "gov",
    "category": "public"
  },
  {
    "id": "netanya_pub_9",
    "lat": 32.3275144,
    "lon": 34.8673547,
    "name": "מקלט 9 - יוספטל 27",
    "address": "יוספטל 27",
    "city": "נתניה",
    "neighborhood": "נאות הרצל",
    "capacity": "",
    "type": "מקלט ציבורי",
    "source": "gov",
    "category": "public"
  },
  {
    "id": "netanya_pub_10",
    "lat": 32.3276032,
    "lon": 34.8654963,
    "name": "מקלט 10 - עולי הגרדום 27",
    "address": "עולי הגרדום 27",
    "city": "נתניה",
    "neighborhood": "סלע",
    "capacity": "",
    "type": "מקלט ציבורי",
    "source": "gov",
    "category": "public"
  },
  {
    "id": "netanya_pub_11",
    "lat": 32.3413639,
    "lon": 34.862599,
    "name": "מקלט 11 - יצחק שדה 7",
    "address": "יצחק שדה 7",
    "city": "נתניה",
    "neighborhood": "",
    "capacity": "",
    "type": "מקלט ציבורי",
    "source": "gov",
    "category": "public"
  },
  {
    "id": "netanya_pub_12",
    "lat": 32.3409039,
    "lon": 34.8649137,
    "name": "מקלט 12 - טרומפלדור 36",
    "address": "טרומפלדור 36",
    "city": "נתניה",
    "neighborhood": "מרכז העיר",
    "capacity": "",
    "type": "מקלט ציבורי",
    "source": "gov",
    "category": "public"
  },
  {
    "id": "netanya_pub_13",
    "lat": 32.3400455,
    "lon": 34.8612479,
    "name": "מקלט 13 - בארי 61",
    "address": "בארי 61",
    "city": "נתניה",
    "neighborhood": "מרכז העיר",
    "capacity": "",
    "type": "מקלט ציבורי",
    "source": "gov",
    "category": "public"
  },
  {
    "id": "netanya_pub_14",
    "lat": 32.3409413,
    "lon": 34.8709557,
    "name": "מקלט 15 - בר יוחאי 20",
    "address": "בר יוחאי 20",
    "city": "נתניה",
    "neighborhood": "נאות הרצל",
    "capacity": "",
    "type": "מקלט ציבורי",
    "source": "gov",
    "category": "public"
  },
  {
    "id": "netanya_pub_15",
    "lat": 32.3415057,
    "lon": 34.8695064,
    "name": "מקלט 16 - בר יוחאי 1",
    "address": "בר יוחאי 1",
    "city": "נתניה",
    "neighborhood": "נאות הרצל",
    "capacity": "",
    "type": "מקלט ציבורי",
    "source": "gov",
    "category": "public"
  },
  {
    "id": "netanya_pub_16",
    "lat": 32.3367911,
    "lon": 34.8696928,
    "name": "מקלט 17 - יוחנן הסנדלר 12",
    "address": "יוחנן הסנדלר 12",
    "city": "נתניה",
    "neighborhood": "נאות הרצל",
    "capacity": "",
    "type": "מקלט ציבורי",
    "source": "gov",
    "category": "public"
  },
  {
    "id": "netanya_pub_17",
    "lat": 32.3367773,
    "lon": 34.866544,
    "name": "מקלט 18 - דב הוז 6",
    "address": "דב הוז 6",
    "city": "נתניה",
    "neighborhood": "נאות הרצל",
    "capacity": "",
    "type": "מקלט ציבורי",
    "source": "gov",
    "category": "public"
  },
  {
    "id": "netanya_pub_19",
    "lat": 32.3276231,
    "lon": 34.867204,
    "name": "מקלט 20 - יוספטל 25",
    "address": "יוספטל 25",
    "city": "נתניה",
    "neighborhood": "נאות הרצל",
    "capacity": "",
    "type": "מקלט ציבורי",
    "source": "gov",
    "category": "public"
  },
  {
    "id": "netanya_pub_20",
    "lat": 32.3341526,
    "lon": 34.8709289,
    "name": "מקלט 21 - שמשון 21",
    "address": "שמשון 21",
    "city": "נתניה",
    "neighborhood": "נאות הרצל",
    "capacity": "",
    "type": "מקלט ציבורי",
    "source": "gov",
    "category": "public"
  },
  {
    "id": "netanya_pub_22",
    "lat": 32.3360235,
    "lon": 34.8558636,
    "name": "מקלט 23 - בורוכוב 5",
    "address": "בורוכוב 5",
    "city": "נתניה",
    "neighborhood": "מרכז העיר",
    "capacity": "",
    "type": "מקלט ציבורי",
    "source": "gov",
    "category": "public"
  },
  {
    "id": "netanya_pub_23",
    "lat": 32.3366736,
    "lon": 34.8574644,
    "name": "מקלט 24 - קפלנסקי 6",
    "address": "קפלנסקי 6",
    "city": "נתניה",
    "neighborhood": "מרכז העיר",
    "capacity": "",
    "type": "מקלט ציבורי",
    "source": "gov",
    "category": "public"
  },
  {
    "id": "netanya_pub_24",
    "lat": 32.3330551,
    "lon": 34.8688589,
    "name": "מקלט 27 - גדעון 11",
    "address": "גדעון 11",
    "city": "נתניה",
    "neighborhood": "נאות הרצל",
    "capacity": "",
    "type": "מקלט ציבורי",
    "source": "gov",
    "category": "public"
  },
  {
    "id": "netanya_pub_25",
    "lat": 32.3284526,
    "lon": 34.8673857,
    "name": "מקלט 29 - יוספטל 10",
    "address": "יוספטל 10",
    "city": "נתניה",
    "neighborhood": "נאות הרצל",
    "capacity": "",
    "type": "מקלט ציבורי",
    "source": "gov",
    "category": "public"
  },
  {
    "id": "netanya_pub_26",
    "lat": 32.3333852,
    "lon": 34.868943,
    "name": "מקלט 30 - ברק בן אבינועם 12",
    "address": "ברק בן אבינועם 12",
    "city": "נתניה",
    "neighborhood": "נאות הרצל",
    "capacity": "",
    "type": "מקלט ציבורי",
    "source": "gov",
    "category": "public"
  },
  {
    "id": "netanya_pub_27",
    "lat": 32.3181328,
    "lon": 34.8853224,
    "name": "מקלט 38 - שרה מלכין 11",
    "address": "שרה מלכין 11",
    "city": "נתניה",
    "neighborhood": "נאות גנים",
    "capacity": "",
    "type": "מקלט ציבורי",
    "source": "gov",
    "category": "public"
  },
  {
    "id": "netanya_pub_28",
    "lat": 32.3200672,
    "lon": 34.8852516,
    "name": "מקלט 39 - קפלן 20",
    "address": "קפלן 20",
    "city": "נתניה",
    "neighborhood": "נאות גנים",
    "capacity": "",
    "type": "מקלט ציבורי",
    "source": "gov",
    "category": "public"
  },
  {
    "id": "netanya_pub_30",
    "lat": 32.3202712,
    "lon": 34.8885863,
    "name": "מקלט 41 - אלומות 31",
    "address": "אלומות 31",
    "city": "נתניה",
    "neighborhood": "נאות גנים",
    "capacity": "",
    "type": "מקלט ציבורי",
    "source": "gov",
    "category": "public"
  },
  {
    "id": "netanya_pub_31",
    "lat": 32.3200672,
    "lon": 34.8852516,
    "name": "מקלט 42 - קפלן 32",
    "address": "קפלן 32",
    "city": "נתניה",
    "neighborhood": "נאות גנים",
    "capacity": "",
    "type": "מקלט ציבורי",
    "source": "gov",
    "category": "public"
  },
  {
    "id": "netanya_pub_32",
    "lat": 32.3206776,
    "lon": 34.8871442,
    "name": "מקלט 43 - סירקין 21",
    "address": "סירקין 21",
    "city": "נתניה",
    "neighborhood": "נאות גנים",
    "capacity": "",
    "type": "מקלט ציבורי",
    "source": "gov",
    "category": "public"
  },
  {
    "id": "netanya_pub_33",
    "lat": 32.3162711,
    "lon": 34.8841755,
    "name": "מקלט 44 - ויתקין 29",
    "address": "ויתקין 29",
    "city": "נתניה",
    "neighborhood": "נאות גנים",
    "capacity": "",
    "type": "מקלט ציבורי",
    "source": "gov",
    "category": "public"
  },
  {
    "id": "netanya_pub_36",
    "lat": 32.3134269,
    "lon": 34.8831427,
    "name": "מקלט 47 - שפרינצק 20",
    "address": "שפרינצק 20",
    "city": "נתניה",
    "neighborhood": "נאות גנים",
    "capacity": "",
    "type": "מקלט ציבורי",
    "source": "gov",
    "category": "public"
  },
  {
    "id": "netanya_pub_37",
    "lat": 32.3162418,
    "lon": 34.8894756,
    "name": "מקלט 48 - עובדיה 32",
    "address": "עובדיה 32",
    "city": "נתניה",
    "neighborhood": "נאות גנים",
    "capacity": "",
    "type": "מקלט ציבורי",
    "source": "gov",
    "category": "public"
  },
  {
    "id": "netanya_pub_38",
    "lat": 32.3134269,
    "lon": 34.8831427,
    "name": "מקלט 49 - שפרינצק 35",
    "address": "שפרינצק 35",
    "city": "נתניה",
    "neighborhood": "נאות גנים",
    "capacity": "",
    "type": "מקלט ציבורי",
    "source": "gov",
    "category": "public"
  },
  {
    "id": "netanya_pub_39",
    "lat": 32.3201791,
    "lon": 34.8494596,
    "name": "מקלט 50 - הלפרין 10",
    "address": "הלפרין 10",
    "city": "נתניה",
    "neighborhood": "נאות גנים",
    "capacity": "",
    "type": "מקלט ציבורי",
    "source": "gov",
    "category": "public"
  },
  {
    "id": "netanya_pub_40",
    "lat": 32.3141464,
    "lon": 34.8818433,
    "name": "מקלט 51 - זייד 18",
    "address": "זייד 18",
    "city": "נתניה",
    "neighborhood": "נאות גנים",
    "capacity": "",
    "type": "מקלט ציבורי",
    "source": "gov",
    "category": "public"
  },
  {
    "id": "netanya_pub_42",
    "lat": 32.3099967,
    "lon": 34.8838699,
    "name": "מקלט 53 - גולד 14",
    "address": "גולד 14",
    "city": "נתניה",
    "neighborhood": "נאות גנים",
    "capacity": "",
    "type": "מקלט ציבורי",
    "source": "gov",
    "category": "public"
  },
  {
    "id": "netanya_pub_45",
    "lat": 32.3118311,
    "lon": 34.8776466,
    "name": "מקלט 56 - שמואל דיין 5",
    "address": "שמואל דיין 5",
    "city": "נתניה",
    "neighborhood": "נאות גנים",
    "capacity": "",
    "type": "מקלט ציבורי",
    "source": "gov",
    "category": "public"
  },
  {
    "id": "netanya_pub_46",
    "lat": 32.3118311,
    "lon": 34.8776466,
    "name": "מקלט 57 - שמואל דיין 19",
    "address": "שמואל דיין 19",
    "city": "נתניה",
    "neighborhood": "נאות גנים",
    "capacity": "",
    "type": "מקלט ציבורי",
    "source": "gov",
    "category": "public"
  },
  {
    "id": "netanya_pub_49",
    "lat": 32.322134,
    "lon": 34.865671,
    "name": "מקלט 59 - אנילביץ 15",
    "address": "אנילביץ 15",
    "city": "נתניה",
    "neighborhood": "רמת אפרים",
    "capacity": "",
    "type": "מקלט ציבורי",
    "source": "gov",
    "category": "public"
  },
  {
    "id": "netanya_pub_50",
    "lat": 32.3226268,
    "lon": 34.8632188,
    "name": "מקלט 60 - סטרומה 13",
    "address": "סטרומה 13",
    "city": "נתניה",
    "neighborhood": "רמת אפרים",
    "capacity": "",
    "type": "מקלט ציבורי",
    "source": "gov",
    "category": "public"
  },
  {
    "id": "netanya_pub_53",
    "lat": 32.3159073,
    "lon": 34.8570189,
    "name": "מקלט 65 - עובדיה בן שלום 16",
    "address": "עובדיה בן שלום 16",
    "city": "נתניה",
    "neighborhood": "",
    "capacity": "",
    "type": "מקלט ציבורי",
    "source": "gov",
    "category": "public"
  },
  {
    "id": "netanya_pub_54",
    "lat": 32.318787,
    "lon": 34.8571775,
    "name": "מקלט 66 - בן אליעזר 55",
    "address": "בן אליעזר 55",
    "city": "נתניה",
    "neighborhood": "",
    "capacity": "",
    "type": "מקלט ציבורי",
    "source": "gov",
    "category": "public"
  },
  {
    "id": "netanya_pub_55",
    "lat": 32.314677,
    "lon": 34.8576103,
    "name": "מקלט 67 - שרעבי 15",
    "address": "שרעבי 15",
    "city": "נתניה",
    "neighborhood": "רמת חן",
    "capacity": "",
    "type": "מקלט ציבורי",
    "source": "gov",
    "category": "public"
  },
  {
    "id": "netanya_pub_56",
    "lat": 32.3132691,
    "lon": 34.8576036,
    "name": "מקלט 68 - אלחריזי 7",
    "address": "אלחריזי 7",
    "city": "נתניה",
    "neighborhood": "רמת חן",
    "capacity": "",
    "type": "מקלט ציבורי",
    "source": "gov",
    "category": "public"
  },
  {
    "id": "netanya_pub_58",
    "lat": 32.3136748,
    "lon": 34.8595622,
    "name": "מקלט 70 - אבן עזרא 30",
    "address": "אבן עזרא 30",
    "city": "נתניה",
    "neighborhood": "רמת חן",
    "capacity": "",
    "type": "מקלט ציבורי",
    "source": "gov",
    "category": "public"
  },
  {
    "id": "netanya_pub_59",
    "lat": 32.3110156,
    "lon": 34.8528548,
    "name": "מקלט 71 - הרב ברוד 5",
    "address": "הרב ברוד 5",
    "city": "נתניה",
    "neighborhood": "נוף הטיילת",
    "capacity": "",
    "type": "מקלט ציבורי",
    "source": "gov",
    "category": "public"
  },
  {
    "id": "netanya_pub_60",
    "lat": 32.3211938,
    "lon": 34.8521481,
    "name": "מקלט 75 - אחימאיר 9",
    "address": "אחימאיר 9",
    "city": "נתניה",
    "neighborhood": "",
    "capacity": "",
    "type": "מקלט ציבורי",
    "source": "gov",
    "category": "public"
  },
  {
    "id": "netanya_pub_62",
    "lat": 32.3316355,
    "lon": 34.8564503,
    "name": "מקלט 77 - שמואל 21",
    "address": "שמואל 21",
    "city": "נתניה",
    "neighborhood": "רמת ידין-דורה",
    "capacity": "",
    "type": "מקלט ציבורי",
    "source": "gov",
    "category": "public"
  },
  {
    "id": "netanya_pub_63",
    "lat": 32.3012362,
    "lon": 34.8567084,
    "name": "מקלט 78 - יחזקאל 34",
    "address": "יחזקאל 34",
    "city": "נתניה",
    "neighborhood": "רמת ידין-דורה",
    "capacity": "",
    "type": "מקלט ציבורי",
    "source": "gov",
    "category": "public"
  },
  {
    "id": "netanya_pub_65",
    "lat": 32.3020831,
    "lon": 34.855987,
    "name": "מקלט 80 - קדושי עיראק 20",
    "address": "קדושי עיראק 20",
    "city": "נתניה",
    "neighborhood": "רמת ידין-דורה",
    "capacity": "",
    "type": "מקלט ציבורי",
    "source": "gov",
    "category": "public"
  },
  {
    "id": "netanya_pub_67",
    "lat": 32.2986277,
    "lon": 34.8559605,
    "name": "מקלט 82 - יחזקאל 30",
    "address": "יחזקאל 30",
    "city": "נתניה",
    "neighborhood": "רמת ידין-דורה",
    "capacity": "",
    "type": "מקלט ציבורי",
    "source": "gov",
    "category": "public"
  },
  {
    "id": "netanya_pub_68",
    "lat": 32.3004892,
    "lon": 34.8551848,
    "name": "מקלט 83 - נחום 11",
    "address": "נחום 11",
    "city": "נתניה",
    "neighborhood": "רמת ידין-דורה",
    "capacity": "",
    "type": "מקלט ציבורי",
    "source": "gov",
    "category": "public"
  },
  {
    "id": "netanya_pub_69",
    "lat": 32.3008614,
    "lon": 34.8584025,
    "name": "מקלט 84 - נחום 13",
    "address": "נחום 13",
    "city": "נתניה",
    "neighborhood": "רמת ידין-דורה",
    "capacity": "",
    "type": "מקלט ציבורי",
    "source": "gov",
    "category": "public"
  },
  {
    "id": "netanya_pub_70",
    "lat": 32.2830859,
    "lon": 34.8570587,
    "name": "מקלט 89 - נורדאו 51",
    "address": "נורדאו 51",
    "city": "נתניה",
    "neighborhood": "קרית נורדאו",
    "capacity": "",
    "type": "מקלט ציבורי",
    "source": "gov",
    "category": "public"
  },
  {
    "id": "netanya_pub_71",
    "lat": 32.2823115,
    "lon": 34.8485858,
    "name": "מקלט 90 - קרן היסוד 5",
    "address": "קרן היסוד 5",
    "city": "נתניה",
    "neighborhood": "קרית נורדאו",
    "capacity": "",
    "type": "מקלט ציבורי",
    "source": "gov",
    "category": "public"
  },
  {
    "id": "netanya_pub_72",
    "lat": 32.3285717,
    "lon": 34.8586886,
    "name": "מקלט 91 - ויצמן 4",
    "address": "ויצמן 4",
    "city": "נתניה",
    "neighborhood": "קרית נורדאו",
    "capacity": "",
    "type": "מקלט ציבורי",
    "source": "gov",
    "category": "public"
  },
  {
    "id": "netanya_pub_73",
    "lat": 32.2823115,
    "lon": 34.8485858,
    "name": "מקלט 96 - קרן היסוד 5",
    "address": "קרן היסוד 5",
    "city": "נתניה",
    "neighborhood": "קרית נורדאו",
    "capacity": "",
    "type": "מקלט ציבורי",
    "source": "gov",
    "category": "public"
  }
]